.editorconfig
.gitignore
.travis.yml
AUTHORS.rst
CONTRIBUTING.rst
HISTORY.rst
LICENSE
MANIFEST.in
Makefile
README.rst
requirements.txt
requirements_dev.txt
requirements_test.txt
runtests.py
setup.cfg
setup.py
tox.ini
.github/ISSUE_TEMPLATE.md
django_price_level.egg-info/PKG-INFO
django_price_level.egg-info/SOURCES.txt
django_price_level.egg-info/dependency_links.txt
django_price_level.egg-info/not-zip-safe
django_price_level.egg-info/requires.txt
django_price_level.egg-info/top_level.txt
docs/Makefile
docs/authors.rst
docs/conf.py
docs/contributing.rst
docs/history.rst
docs/index.rst
docs/installation.rst
docs/make.bat
docs/readme.rst
docs/usage.rst
price_level/__init__.py
price_level/admin.py
price_level/apps.py
price_level/models/__init__.py
price_level/models/pricable.py
price_level/models/priceLevel.py
tests/__init__.py
tests/models.py
tests/test_models.py
tests/test_pricable.py